calculus_ratiocinator/__init__.py
calculus_ratiocinator-0.0.2.dist-info/LICENSE
calculus_ratiocinator-0.0.2.dist-info/METADATA
calculus_ratiocinator-0.0.2.dist-info/WHEEL
calculus_ratiocinator-0.0.2.dist-info/top_level.txt
calculus_ratiocinator-0.0.2.dist-info/RECORD
