Metadata-Version: 2.1
Name: calculus-ratiocinator
Version: 0.0.2
Summary: Calculus Ratiocinator
Author-email: Alexander Fedotov <alex.fedotov@aol.com>
Project-URL: Homepage, https://github.com/calculus-ratiocinator/calculus-ratiocinator
Project-URL: Bug Tracker, https://github.com/calculus-ratiocinator/calculus-ratiocinator/issues
Classifier: Programming Language :: Python :: 3
Classifier: License :: OSI Approved :: MIT License
Classifier: Operating System :: OS Independent
Requires-Python: >=3.10
License-File: LICENSE
